LICENSE
README.md
blazemetrics-0.1.6.dist-info/METADATA
blazemetrics-0.1.6.dist-info/WHEEL
blazemetrics-0.1.6.dist-info/entry_points.txt
blazemetrics-0.1.6.dist-info/licenses/LICENSE
blazemetrics/__init__.py
blazemetrics/agent_eval.py
blazemetrics/agentic.py
blazemetrics/blazemetrics_core.abi3.so
blazemetrics/client.py
blazemetrics/code_evaluator.py
blazemetrics/dashboard.py
blazemetrics/dashboard/__init__.py
blazemetrics/dashboard/__main__.py
blazemetrics/dashboard/api.py
blazemetrics/dashboard/app.py
blazemetrics/dashboard/callbacks.py
blazemetrics/dashboard/layout.py
blazemetrics/dashboard/llm_guardrail_server.py
blazemetrics/enhanced_guardrails.py
blazemetrics/exporters.py
blazemetrics/factuality_evaluator.py
blazemetrics/guardrails.py
blazemetrics/guardrails_pipeline.py
blazemetrics/llm_guardrails.py
blazemetrics/llm_integrations.py
blazemetrics/llm_judge.py
blazemetrics/metrics.py
blazemetrics/monitor.py
blazemetrics/multimodal.py
blazemetrics/production_monitor.py
blazemetrics/py.typed
blazemetrics/reporting.py
blazemetrics/safety_evaluator.py
blazemetrics/streaming_analytics.py
blazemetrics-0.1.6.dist-info/RECORD
