Metadata-Version: 2.4
Name: blazemetrics
Version: 0.1.6
Classifier: License :: OSI Approved :: MIT License
Classifier: Operating System :: OS Independent
Classifier: Programming Language :: Python :: 3
Classifier: Programming Language :: Python :: 3 :: Only
Classifier: Programming Language :: Python :: 3.8
Classifier: Programming Language :: Python :: 3.9
Classifier: Programming Language :: Python :: 3.10
Classifier: Programming Language :: Python :: 3.11
Classifier: Programming Language :: Python :: 3.12
Classifier: Programming Language :: Python :: Implementation :: CPython
Classifier: Topic :: Scientific/Engineering :: Artificial Intelligence
Requires-Dist: numpy
Requires-Dist: dash>=2.0.0 ; extra == 'dashboard'
Requires-Dist: fastapi>=0.101.0 ; extra == 'dashboard'
Requires-Dist: uvicorn>=0.22.0 ; extra == 'dashboard'
Requires-Dist: requests ; extra == 'dashboard'
Requires-Dist: starlette ; extra == 'dashboard'
Requires-Dist: prometheus-client ; extra == 'dashboard'
Requires-Dist: statsd ; extra == 'dashboard'
Provides-Extra: dashboard
License-File: LICENSE
Summary: A high-performance NLP evaluation metrics library with a Rust core.
Home-Page: https://github.com/2796gaur/blazemetrics
Author-email: Gaurav <2796gaurav@gmail.com>
Requires-Python: >=3.8
Project-URL: Homepage, https://github.com/2796gaurav/blazemetrics
Project-URL: Repository, https://github.com/2796gaurav/blazemetrics
Project-URL: Issues, https://github.com/2796gaurav/blazemetrics/issues
